Compiled from "MyJVeganAnimal.java"
public class com.typosafe.java.animals.MyJVeganAnimal implements com.typosafe.java.animals.JAnimal {
  private com.typosafe.java.animals.JAnimal animal;

  com.typosafe.java.animals.MyJVeganAnimal(com.typosafe.java.animals.JAnimal);
    Code:
       0: aload_0
       1: invokespecial #1                  // Method java/lang/Object."<init>":()V
       4: aload_0
       5: aload_1
       6: putfield      #2                  // Field animal:Lcom/typosafe/java/animals/JAnimal;
       9: return

  public java.lang.String eats();
    Code:
       0: aload_0
       1: getfield      #2                  // Field animal:Lcom/typosafe/java/animals/JAnimal;
       4: invokeinterface #3,  1            // InterfaceMethod com/typosafe/java/animals/JAnimal.eats:()Ljava/lang/String;
       9: areturn

  public java.lang.String name();
    Code:
       0: new           #4                  // class java/lang/StringBuilder
       3: dup
       4: invokespecial #5                  // Method java/lang/StringBuilder."<init>":()V
       7: ldc           #6                  // String My
       9: invokevirtual #7                  // Method java/lang/StringBuilder.append:(Ljava/lang/String;)Ljava/lang/StringBuilder;
      12: aload_0
      13: getfield      #2                  // Field animal:Lcom/typosafe/java/animals/JAnimal;
      16: invokeinterface #8,  1            // InterfaceMethod com/typosafe/java/animals/JAnimal.name:()Ljava/lang/String;
      21: invokevirtual #7                  // Method java/lang/StringBuilder.append:(Ljava/lang/String;)Ljava/lang/StringBuilder;
      24: invokevirtual #9                  // Method java/lang/StringBuilder.toString:()Ljava/lang/String;
      27: areturn
}
