Compiled from "KAnimal.kt"
public final class com.typosafe.kotlin.animals.MyKVeganAnimal implements com.typosafe.java.animals.JAnimal {
  private final com.typosafe.kotlin.animals.KVeganAnimal animal;

  public java.lang.String name();
    Code:
       0: new           #11                 // class java/lang/StringBuilder
       3: dup
       4: invokespecial #15                 // Method java/lang/StringBuilder."<init>":()V
       7: ldc           #17                 // String My
       9: invokevirtual #21                 // Method java/lang/StringBuilder.append:(Ljava/lang/String;)Ljava/lang/StringBuilder;
      12: aload_0
      13: getfield      #25                 // Field animal:Lcom/typosafe/kotlin/animals/KVeganAnimal;
      16: invokevirtual #29                 // Method com/typosafe/kotlin/animals/KVeganAnimal.name:()Ljava/lang/String;
      19: invokevirtual #21                 // Method java/lang/StringBuilder.append:(Ljava/lang/String;)Ljava/lang/StringBuilder;
      22: invokevirtual #32                 // Method java/lang/StringBuilder.toString:()Ljava/lang/String;
      25: areturn

  public final com.typosafe.kotlin.animals.KVeganAnimal getAnimal();
    Code:
       0: aload_0
       1: getfield      #25                 // Field animal:Lcom/typosafe/kotlin/animals/KVeganAnimal;
       4: areturn

  public com.typosafe.kotlin.animals.MyKVeganAnimal(com.typosafe.kotlin.animals.KVeganAnimal);
    Code:
       0: aload_1
       1: ldc           #38                 // String animal
       3: invokestatic  #44                 // Method kotlin/jvm/internal/Intrinsics.checkParameterIsNotNull:(Ljava/lang/Object;Ljava/lang/String;)V
       6: aload_0
       7: invokespecial #45                 // Method java/lang/Object."<init>":()V
      10: aload_0
      11: aload_1
      12: putfield      #25                 // Field animal:Lcom/typosafe/kotlin/animals/KVeganAnimal;
      15: return

  public java.lang.String eats();
    Code:
       0: aload_0
       1: getfield      #25                 // Field animal:Lcom/typosafe/kotlin/animals/KVeganAnimal;
       4: invokevirtual #48                 // Method com/typosafe/kotlin/animals/KVeganAnimal.eats:()Ljava/lang/String;
       7: areturn
}
