Compiled from "LazyPropertu.kt"
final class com.typosafe.kotlin.LazyPropertyPublicationSynch$name$2 extends kotlin.jvm.internal.Lambda implements kotlin.jvm.functions.Function0<java.lang.String> {
  final com.typosafe.kotlin.LazyPropertyPublicationSynch this$0;

  public java.lang.Object invoke();
    Code:
       0: aload_0
       1: invokevirtual #12                 // Method invoke:()Ljava/lang/String;
       4: areturn

  public final java.lang.String invoke();
    Code:
       0: new           #15                 // class java/lang/StringBuilder
       3: dup
       4: invokespecial #19                 // Method java/lang/StringBuilder."<init>":()V
       7: ldc           #21                 // String current name
       9: invokevirtual #25                 // Method java/lang/StringBuilder.append:(Ljava/lang/String;)Ljava/lang/StringBuilder;
      12: aload_0
      13: getfield      #29                 // Field this$0:Lcom/typosafe/kotlin/LazyPropertyPublicationSynch;
      16: invokestatic  #35                 // Method com/typosafe/kotlin/LazyPropertyPublicationSynch.access$getInitial$p:(Lcom/typosafe/kotlin/LazyPropertyPublicationSynch;)Ljava/lang/String;
      19: invokevirtual #25                 // Method java/lang/StringBuilder.append:(Ljava/lang/String;)Ljava/lang/StringBuilder;
      22: invokevirtual #38                 // Method java/lang/StringBuilder.toString:()Ljava/lang/String;
      25: areturn

  com.typosafe.kotlin.LazyPropertyPublicationSynch$name$2(com.typosafe.kotlin.LazyPropertyPublicationSynch);
    Code:
       0: aload_0
       1: aload_1
       2: putfield      #29                 // Field this$0:Lcom/typosafe/kotlin/LazyPropertyPublicationSynch;
       5: aload_0
       6: iconst_0
       7: invokespecial #44                 // Method kotlin/jvm/internal/Lambda."<init>":(I)V
      10: return
}
