Compiled from "PojoBench.java"
public class com.typosafe.jmh.PojoBench {
  public com.typosafe.jmh.PojoBench();
    Code:
       0: aload_0
       1: invokespecial #1                  // Method java/lang/Object."<init>":()V
       4: return

  public void testPojoJava(org.openjdk.jmh.infra.Blackhole);
    Code:
       0: new           #2                  // class com/typosafe/java/Pojo
       3: dup
       4: invokespecial #3                  // Method com/typosafe/java/Pojo."<init>":()V
       7: astore_2
       8: getstatic     #4                  // Field com/typosafe/Instances.logins:Ljava/util/List;
      11: invokeinterface #5,  1            // InterfaceMethod java/util/List.iterator:()Ljava/util/Iterator;
      16: astore_3
      17: aload_3
      18: invokeinterface #6,  1            // InterfaceMethod java/util/Iterator.hasNext:()Z
      23: ifeq          54
      26: aload_3
      27: invokeinterface #7,  1            // InterfaceMethod java/util/Iterator.next:()Ljava/lang/Object;
      32: checkcast     #8                  // class java/lang/String
      35: astore        4
      37: aload_2
      38: aload         4
      40: invokevirtual #9                  // Method com/typosafe/java/Pojo.setName:(Ljava/lang/String;)V
      43: aload_1
      44: aload_2
      45: invokevirtual #10                 // Method com/typosafe/java/Pojo.getName:()Ljava/lang/String;
      48: invokevirtual #11                 // Method org/openjdk/jmh/infra/Blackhole.consume:(Ljava/lang/Object;)V
      51: goto          17
      54: return

  public void testPojoKotlin(org.openjdk.jmh.infra.Blackhole);
    Code:
       0: new           #12                 // class com/typosafe/kotlin/Pojo
       3: dup
       4: invokespecial #13                 // Method com/typosafe/kotlin/Pojo."<init>":()V
       7: astore_2
       8: getstatic     #4                  // Field com/typosafe/Instances.logins:Ljava/util/List;
      11: invokeinterface #5,  1            // InterfaceMethod java/util/List.iterator:()Ljava/util/Iterator;
      16: astore_3
      17: aload_3
      18: invokeinterface #6,  1            // InterfaceMethod java/util/Iterator.hasNext:()Z
      23: ifeq          54
      26: aload_3
      27: invokeinterface #7,  1            // InterfaceMethod java/util/Iterator.next:()Ljava/lang/Object;
      32: checkcast     #8                  // class java/lang/String
      35: astore        4
      37: aload_2
      38: aload         4
      40: invokevirtual #14                 // Method com/typosafe/kotlin/Pojo.setName:(Ljava/lang/String;)V
      43: aload_1
      44: aload_2
      45: invokevirtual #15                 // Method com/typosafe/kotlin/Pojo.getName:()Ljava/lang/String;
      48: invokevirtual #11                 // Method org/openjdk/jmh/infra/Blackhole.consume:(Ljava/lang/Object;)V
      51: goto          17
      54: return

  public void testPojoKotlinDataClass(org.openjdk.jmh.infra.Blackhole);
    Code:
       0: new           #16                 // class com/typosafe/kotlin/DataPojo
       3: dup
       4: ldc           #17                 // String ala
       6: bipush        123
       8: invokespecial #18                 // Method com/typosafe/kotlin/DataPojo."<init>":(Ljava/lang/String;I)V
      11: astore_2
      12: getstatic     #4                  // Field com/typosafe/Instances.logins:Ljava/util/List;
      15: invokeinterface #5,  1            // InterfaceMethod java/util/List.iterator:()Ljava/util/Iterator;
      20: astore_3
      21: aload_3
      22: invokeinterface #6,  1            // InterfaceMethod java/util/Iterator.hasNext:()Z
      27: ifeq          58
      30: aload_3
      31: invokeinterface #7,  1            // InterfaceMethod java/util/Iterator.next:()Ljava/lang/Object;
      36: checkcast     #8                  // class java/lang/String
      39: astore        4
      41: aload_2
      42: aload         4
      44: invokevirtual #19                 // Method com/typosafe/kotlin/DataPojo.setName:(Ljava/lang/String;)V
      47: aload_1
      48: aload_2
      49: invokevirtual #20                 // Method com/typosafe/kotlin/DataPojo.getName:()Ljava/lang/String;
      52: invokevirtual #11                 // Method org/openjdk/jmh/infra/Blackhole.consume:(Ljava/lang/Object;)V
      55: goto          21
      58: return
}
