Compiled from "PropertyDelegateBench.java"
public class com.typosafe.jmh.PropertyDelegateBench {
  public com.typosafe.jmh.PropertyDelegateBench();
    Code:
       0: aload_0
       1: invokespecial #1                  // Method java/lang/Object."<init>":()V
       4: return

  public void testPropertyDelegateBaseline(org.openjdk.jmh.infra.Blackhole);
    Code:
       0: new           #2                  // class com/typosafe/kotlin/Pojo
       3: dup
       4: invokespecial #3                  // Method com/typosafe/kotlin/Pojo."<init>":()V
       7: astore_2
       8: getstatic     #4                  // Field com/typosafe/Instances.logins:Ljava/util/List;
      11: invokeinterface #5,  1            // InterfaceMethod java/util/List.iterator:()Ljava/util/Iterator;
      16: astore_3
      17: aload_3
      18: invokeinterface #6,  1            // InterfaceMethod java/util/Iterator.hasNext:()Z
      23: ifeq          57
      26: aload_3
      27: invokeinterface #7,  1            // InterfaceMethod java/util/Iterator.next:()Ljava/lang/Object;
      32: checkcast     #8                  // class java/lang/String
      35: astore        4
      37: aload_2
      38: aload         4
      40: invokevirtual #9                  // Method java/lang/String.toLowerCase:()Ljava/lang/String;
      43: invokevirtual #10                 // Method com/typosafe/kotlin/Pojo.setName:(Ljava/lang/String;)V
      46: aload_1
      47: aload_2
      48: invokevirtual #11                 // Method com/typosafe/kotlin/Pojo.getName:()Ljava/lang/String;
      51: invokevirtual #12                 // Method org/openjdk/jmh/infra/Blackhole.consume:(Ljava/lang/Object;)V
      54: goto          17
      57: return

  public void testPropertyDelegateJava(org.openjdk.jmh.infra.Blackhole);
    Code:
       0: new           #13                 // class com/typosafe/java/DelegatedPropertyLikeJava
       3: dup
       4: invokespecial #14                 // Method com/typosafe/java/DelegatedPropertyLikeJava."<init>":()V
       7: astore_2
       8: getstatic     #4                  // Field com/typosafe/Instances.logins:Ljava/util/List;
      11: invokeinterface #5,  1            // InterfaceMethod java/util/List.iterator:()Ljava/util/Iterator;
      16: astore_3
      17: aload_3
      18: invokeinterface #6,  1            // InterfaceMethod java/util/Iterator.hasNext:()Z
      23: ifeq          54
      26: aload_3
      27: invokeinterface #7,  1            // InterfaceMethod java/util/Iterator.next:()Ljava/lang/Object;
      32: checkcast     #8                  // class java/lang/String
      35: astore        4
      37: aload_2
      38: aload         4
      40: invokevirtual #15                 // Method com/typosafe/java/DelegatedPropertyLikeJava.setName:(Ljava/lang/String;)V
      43: aload_1
      44: aload_2
      45: invokevirtual #16                 // Method com/typosafe/java/DelegatedPropertyLikeJava.getName:()Ljava/lang/String;
      48: invokevirtual #12                 // Method org/openjdk/jmh/infra/Blackhole.consume:(Ljava/lang/Object;)V
      51: goto          17
      54: return

  public void testPropertyDelegateKotlin(org.openjdk.jmh.infra.Blackhole);
    Code:
       0: new           #17                 // class com/typosafe/kotlin/DelegatedProperty
       3: dup
       4: invokespecial #18                 // Method com/typosafe/kotlin/DelegatedProperty."<init>":()V
       7: astore_2
       8: getstatic     #4                  // Field com/typosafe/Instances.logins:Ljava/util/List;
      11: invokeinterface #5,  1            // InterfaceMethod java/util/List.iterator:()Ljava/util/Iterator;
      16: astore_3
      17: aload_3
      18: invokeinterface #6,  1            // InterfaceMethod java/util/Iterator.hasNext:()Z
      23: ifeq          54
      26: aload_3
      27: invokeinterface #7,  1            // InterfaceMethod java/util/Iterator.next:()Ljava/lang/Object;
      32: checkcast     #8                  // class java/lang/String
      35: astore        4
      37: aload_2
      38: aload         4
      40: invokevirtual #19                 // Method com/typosafe/kotlin/DelegatedProperty.setName:(Ljava/lang/String;)V
      43: aload_1
      44: aload_2
      45: invokevirtual #20                 // Method com/typosafe/kotlin/DelegatedProperty.getName:()Ljava/lang/String;
      48: invokevirtual #12                 // Method org/openjdk/jmh/infra/Blackhole.consume:(Ljava/lang/Object;)V
      51: goto          17
      54: return

  public void testPropertyDelegateKotlinSlow(org.openjdk.jmh.infra.Blackhole);
    Code:
       0: new           #21                 // class com/typosafe/kotlin/ReallySlowDelegate
       3: dup
       4: invokespecial #22                 // Method com/typosafe/kotlin/ReallySlowDelegate."<init>":()V
       7: astore_2
       8: getstatic     #4                  // Field com/typosafe/Instances.logins:Ljava/util/List;
      11: invokeinterface #5,  1            // InterfaceMethod java/util/List.iterator:()Ljava/util/Iterator;
      16: astore_3
      17: aload_3
      18: invokeinterface #6,  1            // InterfaceMethod java/util/Iterator.hasNext:()Z
      23: ifeq          54
      26: aload_3
      27: invokeinterface #7,  1            // InterfaceMethod java/util/Iterator.next:()Ljava/lang/Object;
      32: checkcast     #8                  // class java/lang/String
      35: astore        4
      37: aload_2
      38: aload         4
      40: invokevirtual #23                 // Method com/typosafe/kotlin/ReallySlowDelegate.setName:(Ljava/lang/String;)V
      43: aload_1
      44: aload_2
      45: invokevirtual #24                 // Method com/typosafe/kotlin/ReallySlowDelegate.getName:()Ljava/lang/String;
      48: invokevirtual #12                 // Method org/openjdk/jmh/infra/Blackhole.consume:(Ljava/lang/Object;)V
      51: goto          17
      54: return
}
