Compiled from "SLazyProperty.scala"
public class com.typosafe.scala.Loop {
  private final java.lang.String loop1;

  private final java.lang.String loop2;

  public static void main(java.lang.String[]);
    Code:
       0: getstatic     #16                 // Field com/typosafe/scala/Loop$.MODULE$:Lcom/typosafe/scala/Loop$;
       3: aload_0
       4: invokevirtual #18                 // Method com/typosafe/scala/Loop$.main:([Ljava/lang/String;)V
       7: return

  public static void delayedInit(scala.Function0<scala.runtime.BoxedUnit>);
    Code:
       0: getstatic     #16                 // Field com/typosafe/scala/Loop$.MODULE$:Lcom/typosafe/scala/Loop$;
       3: aload_0
       4: invokevirtual #22                 // Method com/typosafe/scala/Loop$.delayedInit:(Lscala/Function0;)V
       7: return

  public static java.lang.String[] args();
    Code:
       0: getstatic     #16                 // Field com/typosafe/scala/Loop$.MODULE$:Lcom/typosafe/scala/Loop$;
       3: invokevirtual #26                 // Method com/typosafe/scala/Loop$.args:()[Ljava/lang/String;
       6: areturn

  public static void scala$App$_setter_$executionStart_$eq(long);
    Code:
       0: getstatic     #16                 // Field com/typosafe/scala/Loop$.MODULE$:Lcom/typosafe/scala/Loop$;
       3: lload_0
       4: invokevirtual #30                 // Method com/typosafe/scala/Loop$.scala$App$_setter_$executionStart_$eq:(J)V
       7: return

  public static long executionStart();
    Code:
       0: getstatic     #16                 // Field com/typosafe/scala/Loop$.MODULE$:Lcom/typosafe/scala/Loop$;
       3: invokevirtual #34                 // Method com/typosafe/scala/Loop$.executionStart:()J
       6: lreturn

  public static void delayedEndpoint$com$typosafe$scala$Loop$1();
    Code:
       0: getstatic     #16                 // Field com/typosafe/scala/Loop$.MODULE$:Lcom/typosafe/scala/Loop$;
       3: invokevirtual #38                 // Method com/typosafe/scala/Loop$.delayedEndpoint$com$typosafe$scala$Loop$1:()V
       6: return

  public java.lang.String loop1();
    Code:
       0: aload_0
       1: getfield      #44                 // Field loop1:Ljava/lang/String;
       4: areturn

  public java.lang.String loop2();
    Code:
       0: aload_0
       1: getfield      #48                 // Field loop2:Ljava/lang/String;
       4: areturn

  public com.typosafe.scala.Loop();
    Code:
       0: aload_0
       1: invokespecial #51                 // Method java/lang/Object."<init>":()V
       4: aload_0
       5: new           #53                 // class scala/collection/mutable/StringBuilder
       8: dup
       9: invokespecial #54                 // Method scala/collection/mutable/StringBuilder."<init>":()V
      12: ldc           #56                 // String Loop2:
      14: invokevirtual #60                 // Method scala/collection/mutable/StringBuilder.append:(Ljava/lang/Object;)Lscala/collection/mutable/StringBuilder;
      17: aload_0
      18: invokevirtual #62                 // Method loop2:()Ljava/lang/String;
      21: invokevirtual #60                 // Method scala/collection/mutable/StringBuilder.append:(Ljava/lang/Object;)Lscala/collection/mutable/StringBuilder;
      24: invokevirtual #65                 // Method scala/collection/mutable/StringBuilder.toString:()Ljava/lang/String;
      27: putfield      #44                 // Field loop1:Ljava/lang/String;
      30: aload_0
      31: new           #53                 // class scala/collection/mutable/StringBuilder
      34: dup
      35: invokespecial #54                 // Method scala/collection/mutable/StringBuilder."<init>":()V
      38: ldc           #67                 // String Loop1:
      40: invokevirtual #60                 // Method scala/collection/mutable/StringBuilder.append:(Ljava/lang/Object;)Lscala/collection/mutable/StringBuilder;
      43: aload_0
      44: invokevirtual #69                 // Method loop1:()Ljava/lang/String;
      47: invokevirtual #60                 // Method scala/collection/mutable/StringBuilder.append:(Ljava/lang/Object;)Lscala/collection/mutable/StringBuilder;
      50: invokevirtual #65                 // Method scala/collection/mutable/StringBuilder.toString:()Ljava/lang/String;
      53: putfield      #48                 // Field loop2:Ljava/lang/String;
      56: return
}
