Compiled from "Pojo.java"
public class com.typosafe.java.Pojo {
  private java.lang.String name;

  private int age;

  public com.typosafe.java.Pojo();
    Code:
       0: aload_0
       1: invokespecial #1                  // Method java/lang/Object."<init>":()V
       4: aload_0
       5: ldc           #2                  // String Ala
       7: putfield      #3                  // Field name:Ljava/lang/String;
      10: aload_0
      11: iconst_1
      12: putfield      #4                  // Field age:I
      15: return

  public java.lang.String getName();
    Code:
       0: aload_0
       1: getfield      #3                  // Field name:Ljava/lang/String;
       4: areturn

  public void setName(java.lang.String);
    Code:
       0: aload_0
       1: aload_1
       2: putfield      #3                  // Field name:Ljava/lang/String;
       5: return

  public int getAge();
    Code:
       0: aload_0
       1: getfield      #4                  // Field age:I
       4: ireturn

  public void setAge(int);
    Code:
       0: aload_0
       1: iload_1
       2: putfield      #4                  // Field age:I
       5: return

  public static java.lang.String updateFromLoginStatic(com.typosafe.java.Pojo, java.lang.String);
    Code:
       0: aload_0
       1: aload_1
       2: invokevirtual #5                  // Method setName:(Ljava/lang/String;)V
       5: aload_0
       6: aload_1
       7: invokevirtual #6                  // Method java/lang/String.length:()I
      10: invokevirtual #7                  // Method setAge:(I)V
      13: new           #8                  // class java/lang/StringBuilder
      16: dup
      17: invokespecial #9                  // Method java/lang/StringBuilder."<init>":()V
      20: aload_0
      21: invokevirtual #10                 // Method getName:()Ljava/lang/String;
      24: invokevirtual #11                 // Method java/lang/StringBuilder.append:(Ljava/lang/String;)Ljava/lang/StringBuilder;
      27: ldc           #12                 // String -
      29: invokevirtual #11                 // Method java/lang/StringBuilder.append:(Ljava/lang/String;)Ljava/lang/StringBuilder;
      32: aload_0
      33: invokevirtual #13                 // Method getAge:()I
      36: invokevirtual #14                 // Method java/lang/StringBuilder.append:(I)Ljava/lang/StringBuilder;
      39: invokevirtual #15                 // Method java/lang/StringBuilder.toString:()Ljava/lang/String;
      42: areturn
}
