Compiled from "Tests.kt"
final class com.typosafe.kotlin.Tests$1$1 extends kotlin.jvm.internal.Lambda implements kotlin.jvm.functions.Function1<io.kotlintest.TestContext, kotlin.Unit> {
  public static final com.typosafe.kotlin.Tests$1$1 INSTANCE;

  public java.lang.Object invoke(java.lang.Object);
    Code:
       0: aload_0
       1: aload_1
       2: checkcast     #11                 // class io/kotlintest/TestContext
       5: invokevirtual #14                 // Method invoke:(Lio/kotlintest/TestContext;)V
       8: getstatic     #20                 // Field kotlin/Unit.INSTANCE:Lkotlin/Unit;
      11: areturn

  public final void invoke(io.kotlintest.TestContext);
    Code:
       0: aload_1
       1: ldc           #23                 // String receiver$0
       3: invokestatic  #29                 // Method kotlin/jvm/internal/Intrinsics.checkParameterIsNotNull:(Ljava/lang/Object;Ljava/lang/String;)V
       6: iconst_3
       7: anewarray     #31                 // class java/lang/String
      10: dup
      11: iconst_0
      12: ldc           #33                 // String Ala Makota
      14: aastore
      15: dup
      16: iconst_1
      17: ldc           #35                 // String Ola
      19: aastore
      20: dup
      21: iconst_2
      22: ldc           #37                 // String Ala  Mala
      24: aastore
      25: invokestatic  #43                 // Method java/util/Arrays.asList:([Ljava/lang/Object;)Ljava/util/List;
      28: astore_2
      29: iconst_2
      30: anewarray     #31                 // class java/lang/String
      33: dup
      34: iconst_0
      35: ldc           #45                 // String ala_makota
      37: aastore
      38: dup
      39: iconst_1
      40: ldc           #47                 // String ala_mala
      42: aastore
      43: invokestatic  #43                 // Method java/util/Arrays.asList:([Ljava/lang/Object;)Ljava/util/List;
      46: astore_3
      47: getstatic     #53                 // Field com/typosafe/Instances.kotlinLambdas:Lcom/typosafe/kotlin/KotlinLambdas;
      50: aload_2
      51: dup
      52: ldc           #55                 // String original
      54: invokestatic  #58                 // Method kotlin/jvm/internal/Intrinsics.checkExpressionValueIsNotNull:(Ljava/lang/Object;Ljava/lang/String;)V
      57: invokevirtual #64                 // Method com/typosafe/kotlin/KotlinLambdas.filterAndMap:(Ljava/util/List;)Ljava/util/List;
      60: aload_3
      61: invokestatic  #70                 // Method io/kotlintest/DslKt.shouldBe:(Ljava/lang/Object;Ljava/lang/Object;)V
      64: getstatic     #74                 // Field com/typosafe/Instances.javaLambdas:Lcom/typosafe/java/JavaLambdas;
      67: aload_2
      68: invokevirtual #77                 // Method com/typosafe/java/JavaLambdas.filterAndMap:(Ljava/util/List;)Ljava/util/List;
      71: aload_3
      72: invokestatic  #70                 // Method io/kotlintest/DslKt.shouldBe:(Ljava/lang/Object;Ljava/lang/Object;)V
      75: getstatic     #53                 // Field com/typosafe/Instances.kotlinLambdas:Lcom/typosafe/kotlin/KotlinLambdas;
      78: getstatic     #81                 // Field com/typosafe/Instances.logins:Ljava/util/List;
      81: dup
      82: ldc           #82                 // String logins
      84: invokestatic  #58                 // Method kotlin/jvm/internal/Intrinsics.checkExpressionValueIsNotNull:(Ljava/lang/Object;Ljava/lang/String;)V
      87: invokevirtual #64                 // Method com/typosafe/kotlin/KotlinLambdas.filterAndMap:(Ljava/util/List;)Ljava/util/List;
      90: getstatic     #74                 // Field com/typosafe/Instances.javaLambdas:Lcom/typosafe/java/JavaLambdas;
      93: getstatic     #81                 // Field com/typosafe/Instances.logins:Ljava/util/List;
      96: invokevirtual #77                 // Method com/typosafe/java/JavaLambdas.filterAndMap:(Ljava/util/List;)Ljava/util/List;
      99: invokestatic  #70                 // Method io/kotlintest/DslKt.shouldBe:(Ljava/lang/Object;Ljava/lang/Object;)V
     102: return

  com.typosafe.kotlin.Tests$1$1();
    Code:
       0: aload_0
       1: iconst_1
       2: invokespecial #92                 // Method kotlin/jvm/internal/Lambda."<init>":(I)V
       5: return

  static {};
    Code:
       0: new           #2                  // class com/typosafe/kotlin/Tests$1$1
       3: dup
       4: invokespecial #112                // Method "<init>":()V
       7: putstatic     #114                // Field INSTANCE:Lcom/typosafe/kotlin/Tests$1$1;
      10: return
}
