Compiled from "Instances.java"
public class com.typosafe.Instances {
  public static final com.typosafe.kotlin.KotlinMethods kotlinMethods;

  public static final com.typosafe.java.JavaMethods javaMethods;

  public static final com.typosafe.kotlin.KotlinLambdas kotlinLambdas;

  public static final com.typosafe.java.JavaLambdas javaLambdas;

  private static java.util.Random r;

  public static final java.util.List<java.lang.String> logins;

  public static java.util.List<java.lang.Object> randomObjects;

  public com.typosafe.Instances();
    Code:
       0: aload_0
       1: invokespecial #1                  // Method java/lang/Object."<init>":()V
       4: return

  public static java.lang.String printUserList(java.util.function.Function<java.lang.String, java.lang.String>);
    Code:
       0: new           #2                  // class java/lang/StringBuilder
       3: dup
       4: invokespecial #3                  // Method java/lang/StringBuilder."<init>":()V
       7: aload_0
       8: ldc           #4                  // String Ala maKota
      10: invokeinterface #5,  2            // InterfaceMethod java/util/function/Function.apply:(Ljava/lang/Object;)Ljava/lang/Object;
      15: checkcast     #6                  // class java/lang/String
      18: invokevirtual #7                  // Method java/lang/StringBuilder.append:(Ljava/lang/String;)Ljava/lang/StringBuilder;
      21: ldc           #8                  // String \n
      23: invokevirtual #7                  // Method java/lang/StringBuilder.append:(Ljava/lang/String;)Ljava/lang/StringBuilder;
      26: aload_0
      27: ldc           #9                  // String Ula maPsa
      29: invokeinterface #5,  2            // InterfaceMethod java/util/function/Function.apply:(Ljava/lang/Object;)Ljava/lang/Object;
      34: checkcast     #6                  // class java/lang/String
      37: invokevirtual #7                  // Method java/lang/StringBuilder.append:(Ljava/lang/String;)Ljava/lang/StringBuilder;
      40: ldc           #8                  // String \n
      42: invokevirtual #7                  // Method java/lang/StringBuilder.append:(Ljava/lang/String;)Ljava/lang/StringBuilder;
      45: aload_0
      46: ldc           #10                 // String Ala nieMaNic
      48: invokeinterface #5,  2            // InterfaceMethod java/util/function/Function.apply:(Ljava/lang/Object;)Ljava/lang/Object;
      53: checkcast     #6                  // class java/lang/String
      56: invokevirtual #7                  // Method java/lang/StringBuilder.append:(Ljava/lang/String;)Ljava/lang/StringBuilder;
      59: invokevirtual #11                 // Method java/lang/StringBuilder.toString:()Ljava/lang/String;
      62: areturn

  private static java.util.List<java.lang.Object> randomList();
    Code:
       0: new           #12                 // class java/util/ArrayList
       3: dup
       4: invokespecial #13                 // Method java/util/ArrayList."<init>":()V
       7: astore_0
       8: getstatic     #14                 // Field r:Ljava/util/Random;
      11: bipush        20
      13: invokevirtual #15                 // Method java/util/Random.nextInt:(I)I
      16: ifeq          36
      19: aload_0
      20: getstatic     #14                 // Field r:Ljava/util/Random;
      23: invokevirtual #16                 // Method java/util/Random.nextInt:()I
      26: invokestatic  #17                 // Method java/lang/Integer.valueOf:(I)Ljava/lang/Integer;
      29: invokevirtual #18                 // Method java/util/ArrayList.add:(Ljava/lang/Object;)Z
      32: pop
      33: goto          8
      36: aload_0
      37: areturn

  private static java.util.List<java.lang.String> basic();
    Code:
       0: iconst_3
       1: anewarray     #6                  // class java/lang/String
       4: dup
       5: iconst_0
       6: new           #2                  // class java/lang/StringBuilder
       9: dup
      10: invokespecial #3                  // Method java/lang/StringBuilder."<init>":()V
      13: ldc           #19                 // String Ala Makota
      15: invokevirtual #7                  // Method java/lang/StringBuilder.append:(Ljava/lang/String;)Ljava/lang/StringBuilder;
      18: getstatic     #14                 // Field r:Ljava/util/Random;
      21: bipush        100
      23: invokevirtual #15                 // Method java/util/Random.nextInt:(I)I
      26: invokevirtual #20                 // Method java/lang/StringBuilder.append:(I)Ljava/lang/StringBuilder;
      29: invokevirtual #11                 // Method java/lang/StringBuilder.toString:()Ljava/lang/String;
      32: aastore
      33: dup
      34: iconst_1
      35: new           #2                  // class java/lang/StringBuilder
      38: dup
      39: invokespecial #3                  // Method java/lang/StringBuilder."<init>":()V
      42: ldc           #21                 // String Ola
      44: invokevirtual #7                  // Method java/lang/StringBuilder.append:(Ljava/lang/String;)Ljava/lang/StringBuilder;
      47: getstatic     #14                 // Field r:Ljava/util/Random;
      50: bipush        100
      52: invokevirtual #15                 // Method java/util/Random.nextInt:(I)I
      55: invokevirtual #20                 // Method java/lang/StringBuilder.append:(I)Ljava/lang/StringBuilder;
      58: invokevirtual #11                 // Method java/lang/StringBuilder.toString:()Ljava/lang/String;
      61: aastore
      62: dup
      63: iconst_2
      64: new           #2                  // class java/lang/StringBuilder
      67: dup
      68: invokespecial #3                  // Method java/lang/StringBuilder."<init>":()V
      71: ldc           #22                 // String Ala  Mala
      73: invokevirtual #7                  // Method java/lang/StringBuilder.append:(Ljava/lang/String;)Ljava/lang/StringBuilder;
      76: getstatic     #14                 // Field r:Ljava/util/Random;
      79: bipush        100
      81: invokevirtual #15                 // Method java/util/Random.nextInt:(I)I
      84: invokevirtual #20                 // Method java/lang/StringBuilder.append:(I)Ljava/lang/StringBuilder;
      87: invokevirtual #11                 // Method java/lang/StringBuilder.toString:()Ljava/lang/String;
      90: aastore
      91: invokestatic  #23                 // Method java/util/Arrays.asList:([Ljava/lang/Object;)Ljava/util/List;
      94: areturn

  private static java.util.List<java.lang.String> generateLogins();
    Code:
       0: invokedynamic #24,  0             // InvokeDynamic #0:get:()Ljava/util/function/Supplier;
       5: invokestatic  #25                 // InterfaceMethod java/util/stream/Stream.generate:(Ljava/util/function/Supplier;)Ljava/util/stream/Stream;
       8: ldc2_w        #26                 // long 100l
      11: invokeinterface #28,  3           // InterfaceMethod java/util/stream/Stream.limit:(J)Ljava/util/stream/Stream;
      16: invokedynamic #29,  0             // InvokeDynamic #1:apply:()Ljava/util/function/Function;
      21: invokeinterface #30,  2           // InterfaceMethod java/util/stream/Stream.flatMap:(Ljava/util/function/Function;)Ljava/util/stream/Stream;
      26: invokestatic  #31                 // Method java/util/stream/Collectors.toList:()Ljava/util/stream/Collector;
      29: invokeinterface #32,  2           // InterfaceMethod java/util/stream/Stream.collect:(Ljava/util/stream/Collector;)Ljava/lang/Object;
      34: checkcast     #33                 // class java/util/List
      37: areturn

  private static java.util.stream.Stream lambda$static$0(java.lang.String);
    Code:
       0: iconst_3
       1: anewarray     #34                 // class java/lang/Object
       4: dup
       5: iconst_0
       6: invokestatic  #35                 // Method randomList:()Ljava/util/List;
       9: aastore
      10: dup
      11: iconst_1
      12: getstatic     #36                 // Field kotlinLambdas:Lcom/typosafe/kotlin/KotlinLambdas;
      15: aastore
      16: dup
      17: iconst_2
      18: aload_0
      19: aastore
      20: invokestatic  #37                 // InterfaceMethod java/util/stream/Stream.of:([Ljava/lang/Object;)Ljava/util/stream/Stream;
      23: areturn

  static {};
    Code:
       0: new           #38                 // class com/typosafe/kotlin/KotlinMethods
       3: dup
       4: invokespecial #39                 // Method com/typosafe/kotlin/KotlinMethods."<init>":()V
       7: putstatic     #40                 // Field kotlinMethods:Lcom/typosafe/kotlin/KotlinMethods;
      10: new           #41                 // class com/typosafe/java/JavaMethods
      13: dup
      14: invokespecial #42                 // Method com/typosafe/java/JavaMethods."<init>":()V
      17: putstatic     #43                 // Field javaMethods:Lcom/typosafe/java/JavaMethods;
      20: new           #44                 // class com/typosafe/kotlin/KotlinLambdas
      23: dup
      24: invokespecial #45                 // Method com/typosafe/kotlin/KotlinLambdas."<init>":()V
      27: putstatic     #36                 // Field kotlinLambdas:Lcom/typosafe/kotlin/KotlinLambdas;
      30: new           #46                 // class com/typosafe/java/JavaLambdas
      33: dup
      34: invokespecial #47                 // Method com/typosafe/java/JavaLambdas."<init>":()V
      37: putstatic     #48                 // Field javaLambdas:Lcom/typosafe/java/JavaLambdas;
      40: new           #49                 // class java/util/Random
      43: dup
      44: ldc2_w        #50                 // long 556783l
      47: invokespecial #52                 // Method java/util/Random."<init>":(J)V
      50: putstatic     #14                 // Field r:Ljava/util/Random;
      53: invokestatic  #53                 // Method generateLogins:()Ljava/util/List;
      56: putstatic     #54                 // Field logins:Ljava/util/List;
      59: invokestatic  #53                 // Method generateLogins:()Ljava/util/List;
      62: invokeinterface #55,  1           // InterfaceMethod java/util/List.stream:()Ljava/util/stream/Stream;
      67: ldc2_w        #56                 // long 30l
      70: invokeinterface #28,  3           // InterfaceMethod java/util/stream/Stream.limit:(J)Ljava/util/stream/Stream;
      75: invokedynamic #58,  0             // InvokeDynamic #2:apply:()Ljava/util/function/Function;
      80: invokeinterface #30,  2           // InterfaceMethod java/util/stream/Stream.flatMap:(Ljava/util/function/Function;)Ljava/util/stream/Stream;
      85: invokestatic  #31                 // Method java/util/stream/Collectors.toList:()Ljava/util/stream/Collector;
      88: invokeinterface #32,  2           // InterfaceMethod java/util/stream/Stream.collect:(Ljava/util/stream/Collector;)Ljava/lang/Object;
      93: checkcast     #33                 // class java/util/List
      96: putstatic     #59                 // Field randomObjects:Ljava/util/List;
      99: getstatic     #59                 // Field randomObjects:Ljava/util/List;
     102: getstatic     #14                 // Field r:Ljava/util/Random;
     105: invokestatic  #60                 // Method java/util/Collections.shuffle:(Ljava/util/List;Ljava/util/Random;)V
     108: return
}
