Compiled from "Pojo.kt"
public final class com.typosafe.kotlin.Pojo {
  private java.lang.String name;

  private int age;

  public static final com.typosafe.kotlin.Pojo$Companion Companion;

  public final java.lang.String getName();
    Code:
       0: aload_0
       1: getfield      #11                 // Field name:Ljava/lang/String;
       4: areturn

  public final void setName(java.lang.String);
    Code:
       0: aload_1
       1: ldc           #17                 // String <set-?>
       3: invokestatic  #23                 // Method kotlin/jvm/internal/Intrinsics.checkParameterIsNotNull:(Ljava/lang/Object;Ljava/lang/String;)V
       6: aload_0
       7: aload_1
       8: putfield      #11                 // Field name:Ljava/lang/String;
      11: return

  public final int getAge();
    Code:
       0: aload_0
       1: getfield      #29                 // Field age:I
       4: ireturn

  public final void setAge(int);
    Code:
       0: aload_0
       1: iload_1
       2: putfield      #29                 // Field age:I
       5: return

  public com.typosafe.kotlin.Pojo();
    Code:
       0: aload_0
       1: invokespecial #35                 // Method java/lang/Object."<init>":()V
       4: aload_0
       5: ldc           #37                 // String ala
       7: putfield      #11                 // Field name:Ljava/lang/String;
      10: aload_0
      11: bipush        123
      13: putfield      #29                 // Field age:I
      16: return

  static {};
    Code:
       0: new           #55                 // class com/typosafe/kotlin/Pojo$Companion
       3: dup
       4: aconst_null
       5: invokespecial #58                 // Method com/typosafe/kotlin/Pojo$Companion."<init>":(Lkotlin/jvm/internal/DefaultConstructorMarker;)V
       8: putstatic     #60                 // Field Companion:Lcom/typosafe/kotlin/Pojo$Companion;
      11: return
}
