Compiled from "JLazyPropertySync.java"
public class com.typosafe.java.JLazyPropertySync {
  private java.lang.String initial;

  private java.lang.String name;

  public com.typosafe.java.JLazyPropertySync(java.lang.String);
    Code:
       0: aload_0
       1: invokespecial #1                  // Method java/lang/Object."<init>":()V
       4: aload_0
       5: aload_1
       6: putfield      #2                  // Field initial:Ljava/lang/String;
       9: return

  public synchronized java.lang.String getName();
    Code:
       0: aload_0
       1: getfield      #3                  // Field name:Ljava/lang/String;
       4: ifnonnull     33
       7: aload_0
       8: new           #4                  // class java/lang/StringBuilder
      11: dup
      12: invokespecial #5                  // Method java/lang/StringBuilder."<init>":()V
      15: ldc           #6                  // String current name
      17: invokevirtual #7                  // Method java/lang/StringBuilder.append:(Ljava/lang/String;)Ljava/lang/StringBuilder;
      20: aload_0
      21: getfield      #3                  // Field name:Ljava/lang/String;
      24: invokevirtual #7                  // Method java/lang/StringBuilder.append:(Ljava/lang/String;)Ljava/lang/StringBuilder;
      27: invokevirtual #8                  // Method java/lang/StringBuilder.toString:()Ljava/lang/String;
      30: putfield      #3                  // Field name:Ljava/lang/String;
      33: aload_0
      34: getfield      #3                  // Field name:Ljava/lang/String;
      37: areturn
}
