Compiled from "MethodCallsBench.java"
public class com.typosafe.jmh.MethodCallsBench {
  public com.typosafe.jmh.MethodCallsBench();
    Code:
       0: aload_0
       1: invokespecial #1                  // Method java/lang/Object."<init>":()V
       4: return

  public void testMethodJava(org.openjdk.jmh.infra.Blackhole);
    Code:
       0: getstatic     #2                  // Field com/typosafe/Instances.randomObjects:Ljava/util/List;
       3: invokeinterface #3,  1            // InterfaceMethod java/util/List.iterator:()Ljava/util/Iterator;
       8: astore_2
       9: aload_2
      10: invokeinterface #4,  1            // InterfaceMethod java/util/Iterator.hasNext:()Z
      15: ifeq          39
      18: aload_2
      19: invokeinterface #5,  1            // InterfaceMethod java/util/Iterator.next:()Ljava/lang/Object;
      24: astore_3
      25: aload_1
      26: getstatic     #6                  // Field com/typosafe/Instances.javaMethods:Lcom/typosafe/java/JavaMethods;
      29: aload_3
      30: invokevirtual #7                  // Method com/typosafe/java/JavaMethods.size:(Ljava/lang/Object;)I
      33: invokevirtual #8                  // Method org/openjdk/jmh/infra/Blackhole.consume:(I)V
      36: goto          9
      39: return

  public void testMethodKotlin(org.openjdk.jmh.infra.Blackhole);
    Code:
       0: getstatic     #2                  // Field com/typosafe/Instances.randomObjects:Ljava/util/List;
       3: invokeinterface #3,  1            // InterfaceMethod java/util/List.iterator:()Ljava/util/Iterator;
       8: astore_2
       9: aload_2
      10: invokeinterface #4,  1            // InterfaceMethod java/util/Iterator.hasNext:()Z
      15: ifeq          39
      18: aload_2
      19: invokeinterface #5,  1            // InterfaceMethod java/util/Iterator.next:()Ljava/lang/Object;
      24: astore_3
      25: aload_1
      26: getstatic     #9                  // Field com/typosafe/Instances.kotlinMethods:Lcom/typosafe/kotlin/KotlinMethods;
      29: aload_3
      30: invokevirtual #10                 // Method com/typosafe/kotlin/KotlinMethods.size:(Ljava/lang/Object;)I
      33: invokevirtual #8                  // Method org/openjdk/jmh/infra/Blackhole.consume:(I)V
      36: goto          9
      39: return

  public void testSimplerMethodJava(org.openjdk.jmh.infra.Blackhole);
    Code:
       0: getstatic     #11                 // Field com/typosafe/Instances.logins:Ljava/util/List;
       3: invokeinterface #3,  1            // InterfaceMethod java/util/List.iterator:()Ljava/util/Iterator;
       8: astore_2
       9: aload_2
      10: invokeinterface #4,  1            // InterfaceMethod java/util/Iterator.hasNext:()Z
      15: ifeq          42
      18: aload_2
      19: invokeinterface #5,  1            // InterfaceMethod java/util/Iterator.next:()Ljava/lang/Object;
      24: checkcast     #12                 // class java/lang/String
      27: astore_3
      28: aload_1
      29: getstatic     #6                  // Field com/typosafe/Instances.javaMethods:Lcom/typosafe/java/JavaMethods;
      32: aload_3
      33: invokevirtual #13                 // Method com/typosafe/java/JavaMethods.baseLenght:(Ljava/lang/String;)Z
      36: invokevirtual #14                 // Method org/openjdk/jmh/infra/Blackhole.consume:(Z)V
      39: goto          9
      42: return

  public void testSimplerMethodKotlin(org.openjdk.jmh.infra.Blackhole);
    Code:
       0: getstatic     #11                 // Field com/typosafe/Instances.logins:Ljava/util/List;
       3: invokeinterface #3,  1            // InterfaceMethod java/util/List.iterator:()Ljava/util/Iterator;
       8: astore_2
       9: aload_2
      10: invokeinterface #4,  1            // InterfaceMethod java/util/Iterator.hasNext:()Z
      15: ifeq          42
      18: aload_2
      19: invokeinterface #5,  1            // InterfaceMethod java/util/Iterator.next:()Ljava/lang/Object;
      24: checkcast     #12                 // class java/lang/String
      27: astore_3
      28: aload_1
      29: getstatic     #9                  // Field com/typosafe/Instances.kotlinMethods:Lcom/typosafe/kotlin/KotlinMethods;
      32: aload_3
      33: invokevirtual #15                 // Method com/typosafe/kotlin/KotlinMethods.basicLenght:(Ljava/lang/String;)Z
      36: invokevirtual #14                 // Method org/openjdk/jmh/infra/Blackhole.consume:(Z)V
      39: goto          9
      42: return

  public void testSimplerMethodBaseline(org.openjdk.jmh.infra.Blackhole);
    Code:
       0: getstatic     #11                 // Field com/typosafe/Instances.logins:Ljava/util/List;
       3: invokeinterface #3,  1            // InterfaceMethod java/util/List.iterator:()Ljava/util/Iterator;
       8: astore_2
       9: aload_2
      10: invokeinterface #4,  1            // InterfaceMethod java/util/Iterator.hasNext:()Z
      15: ifeq          47
      18: aload_2
      19: invokeinterface #5,  1            // InterfaceMethod java/util/Iterator.next:()Ljava/lang/Object;
      24: checkcast     #12                 // class java/lang/String
      27: astore_3
      28: aload_1
      29: aload_3
      30: invokevirtual #16                 // Method java/lang/String.length:()I
      33: ifle          40
      36: iconst_1
      37: goto          41
      40: iconst_0
      41: invokevirtual #14                 // Method org/openjdk/jmh/infra/Blackhole.consume:(Z)V
      44: goto          9
      47: return

  public int testFibJava();
    Code:
       0: getstatic     #6                  // Field com/typosafe/Instances.javaMethods:Lcom/typosafe/java/JavaMethods;
       3: ldc           #17                 // String 100
       5: invokevirtual #18                 // Method com/typosafe/java/JavaMethods.fib:(Ljava/lang/Object;)I
       8: ireturn

  public int testFibKotlin();
    Code:
       0: getstatic     #9                  // Field com/typosafe/Instances.kotlinMethods:Lcom/typosafe/kotlin/KotlinMethods;
       3: ldc           #17                 // String 100
       5: invokevirtual #19                 // Method com/typosafe/kotlin/KotlinMethods.fib:(Ljava/lang/Object;)I
       8: ireturn
}
