Compiled from "DelegatedProperty.kt"
public final class com.typosafe.kotlin.UppercaseDelegate<T> implements kotlin.properties.ReadWriteProperty<T, java.lang.String> {
  private java.lang.String current;

  public java.lang.String getValue(T, kotlin.reflect.KProperty<?>);
    Code:
       0: aload_2
       1: ldc           #16                 // String property
       3: invokestatic  #22                 // Method kotlin/jvm/internal/Intrinsics.checkParameterIsNotNull:(Ljava/lang/Object;Ljava/lang/String;)V
       6: aload_0
       7: getfield      #26                 // Field current:Ljava/lang/String;
      10: areturn

  public java.lang.Object getValue(java.lang.Object, kotlin.reflect.KProperty);
    Code:
       0: aload_0
       1: aload_1
       2: aload_2
       3: invokevirtual #13                 // Method getValue:(Ljava/lang/Object;Lkotlin/reflect/KProperty;)Ljava/lang/String;
       6: areturn

  public void setValue(T, kotlin.reflect.KProperty<?>, java.lang.String);
    Code:
       0: aload_2
       1: ldc           #16                 // String property
       3: invokestatic  #22                 // Method kotlin/jvm/internal/Intrinsics.checkParameterIsNotNull:(Ljava/lang/Object;Ljava/lang/String;)V
       6: aload_3
       7: ldc           #41                 // String value
       9: invokestatic  #22                 // Method kotlin/jvm/internal/Intrinsics.checkParameterIsNotNull:(Ljava/lang/Object;Ljava/lang/String;)V
      12: aload_0
      13: aload_3
      14: astore        4
      16: astore        5
      18: aload         4
      20: invokevirtual #45                 // Method java/lang/String.toUpperCase:()Ljava/lang/String;
      23: dup
      24: ldc           #47                 // String (this as java.lang.String).toUpperCase()
      26: invokestatic  #50                 // Method kotlin/jvm/internal/Intrinsics.checkExpressionValueIsNotNull:(Ljava/lang/Object;Ljava/lang/String;)V
      29: astore        6
      31: aload         5
      33: aload         6
      35: putfield      #26                 // Field current:Ljava/lang/String;
      38: return

  public void setValue(java.lang.Object, kotlin.reflect.KProperty, java.lang.Object);
    Code:
       0: aload_0
       1: aload_1
       2: aload_2
       3: aload_3
       4: checkcast     #37                 // class java/lang/String
       7: invokevirtual #39                 // Method setValue:(Ljava/lang/Object;Lkotlin/reflect/KProperty;Ljava/lang/String;)V
      10: return

  public com.typosafe.kotlin.UppercaseDelegate(java.lang.String);
    Code:
       0: aload_1
       1: ldc           #53                 // String current
       3: invokestatic  #22                 // Method kotlin/jvm/internal/Intrinsics.checkParameterIsNotNull:(Ljava/lang/Object;Ljava/lang/String;)V
       6: aload_0
       7: invokespecial #56                 // Method java/lang/Object."<init>":()V
      10: aload_0
      11: aload_1
      12: putfield      #26                 // Field current:Ljava/lang/String;
      15: return
}
