Compiled from "SLazyProperty.scala"
public class com.typosafe.scala.SLazyProperty {
  private final java.lang.String initial;

  private java.lang.String name;

  private volatile boolean bitmap$0;

  private java.lang.String name$lzycompute();
    Code:
       0: aload_0
       1: dup
       2: astore_1
       3: monitorenter
       4: aload_0
       5: getfield      #17                 // Field bitmap$0:Z
       8: ifne          42
      11: aload_0
      12: new           #19                 // class scala/collection/mutable/StringBuilder
      15: dup
      16: invokespecial #23                 // Method scala/collection/mutable/StringBuilder."<init>":()V
      19: ldc           #25                 // String current name
      21: invokevirtual #29                 // Method scala/collection/mutable/StringBuilder.append:(Ljava/lang/Object;)Lscala/collection/mutable/StringBuilder;
      24: aload_0
      25: getfield      #31                 // Field initial:Ljava/lang/String;
      28: invokevirtual #29                 // Method scala/collection/mutable/StringBuilder.append:(Ljava/lang/Object;)Lscala/collection/mutable/StringBuilder;
      31: invokevirtual #34                 // Method scala/collection/mutable/StringBuilder.toString:()Ljava/lang/String;
      34: putfield      #36                 // Field name:Ljava/lang/String;
      37: aload_0
      38: iconst_1
      39: putfield      #17                 // Field bitmap$0:Z
      42: getstatic     #42                 // Field scala/runtime/BoxedUnit.UNIT:Lscala/runtime/BoxedUnit;
      45: pop
      46: aload_1
      47: monitorexit
      48: aload_0
      49: aconst_null
      50: putfield      #31                 // Field initial:Ljava/lang/String;
      53: aload_0
      54: getfield      #36                 // Field name:Ljava/lang/String;
      57: areturn
      58: aload_1
      59: monitorexit
      60: athrow
    Exception table:
       from    to  target type
           4    48    58   any

  public java.lang.String name();
    Code:
       0: aload_0
       1: getfield      #17                 // Field bitmap$0:Z
       4: ifeq          14
       7: aload_0
       8: getfield      #36                 // Field name:Ljava/lang/String;
      11: goto          18
      14: aload_0
      15: invokespecial #48                 // Method name$lzycompute:()Ljava/lang/String;
      18: areturn

  public com.typosafe.scala.SLazyProperty(java.lang.String);
    Code:
       0: aload_0
       1: aload_1
       2: putfield      #31                 // Field initial:Ljava/lang/String;
       5: aload_0
       6: invokespecial #52                 // Method java/lang/Object."<init>":()V
       9: return
}
