Compiled from "KAnimal.kt"
public final class com.typosafe.kotlin.animals.KVeganAnimal implements com.typosafe.java.animals.JAnimal {
  private final java.lang.String name;

  public java.lang.String eats();
    Code:
       0: new           #11                 // class java/lang/StringBuilder
       3: dup
       4: invokespecial #15                 // Method java/lang/StringBuilder."<init>":()V
       7: aload_0
       8: getfield      #19                 // Field name:Ljava/lang/String;
      11: invokevirtual #23                 // Method java/lang/StringBuilder.append:(Ljava/lang/String;)Ljava/lang/StringBuilder;
      14: ldc           #25                 // String  eats only grass and stuff
      16: invokevirtual #23                 // Method java/lang/StringBuilder.append:(Ljava/lang/String;)Ljava/lang/StringBuilder;
      19: invokevirtual #28                 // Method java/lang/StringBuilder.toString:()Ljava/lang/String;
      22: areturn

  public java.lang.String name();
    Code:
       0: aload_0
       1: getfield      #19                 // Field name:Ljava/lang/String;
       4: areturn

  public com.typosafe.kotlin.animals.KVeganAnimal(java.lang.String);
    Code:
       0: aload_1
       1: ldc           #32                 // String name
       3: invokestatic  #38                 // Method kotlin/jvm/internal/Intrinsics.checkParameterIsNotNull:(Ljava/lang/Object;Ljava/lang/String;)V
       6: aload_0
       7: invokespecial #39                 // Method java/lang/Object."<init>":()V
      10: aload_0
      11: aload_1
      12: putfield      #19                 // Field name:Ljava/lang/String;
      15: return
}
