Compiled from "Tests.kt"
final class com.typosafe.kotlin.Tests$1$2 extends kotlin.jvm.internal.Lambda implements kotlin.jvm.functions.Function1<io.kotlintest.TestContext, kotlin.Unit> {
  public static final com.typosafe.kotlin.Tests$1$2 INSTANCE;

  public java.lang.Object invoke(java.lang.Object);
    Code:
       0: aload_0
       1: aload_1
       2: checkcast     #11                 // class io/kotlintest/TestContext
       5: invokevirtual #14                 // Method invoke:(Lio/kotlintest/TestContext;)V
       8: getstatic     #20                 // Field kotlin/Unit.INSTANCE:Lkotlin/Unit;
      11: areturn

  public final void invoke(io.kotlintest.TestContext);
    Code:
       0: aload_1
       1: ldc           #23                 // String $receiver
       3: invokestatic  #29                 // Method kotlin/jvm/internal/Intrinsics.checkParameterIsNotNull:(Ljava/lang/Object;Ljava/lang/String;)V
       6: getstatic     #35                 // Field com/typosafe/Instances.javaMethods:Lcom/typosafe/java/JavaMethods;
       9: ldc           #37                 // String 6
      11: invokevirtual #43                 // Method com/typosafe/java/JavaMethods.fib:(Ljava/lang/Object;)I
      14: invokestatic  #49                 // Method java/lang/Integer.valueOf:(I)Ljava/lang/Integer;
      17: bipush        8
      19: invokestatic  #49                 // Method java/lang/Integer.valueOf:(I)Ljava/lang/Integer;
      22: invokestatic  #55                 // Method io/kotlintest/DslKt.shouldBe:(Ljava/lang/Object;Ljava/lang/Object;)V
      25: return

  com.typosafe.kotlin.Tests$1$2();
    Code:
       0: aload_0
       1: iconst_1
       2: invokespecial #63                 // Method kotlin/jvm/internal/Lambda."<init>":(I)V
       5: return

  static {};
    Code:
       0: new           #2                  // class com/typosafe/kotlin/Tests$1$2
       3: dup
       4: invokespecial #84                 // Method "<init>":()V
       7: putstatic     #86                 // Field INSTANCE:Lcom/typosafe/kotlin/Tests$1$2;
      10: return
}
