Compiled from "ExtensionMethodsBench.kt"
public class com.typosafe.jmh.ExtensionMethodsBench {
  public final void javaStaticFunction(org.openjdk.jmh.infra.Blackhole);
    Code:
       0: aload_1
       1: ldc           #26                 // String bh
       3: invokestatic  #32                 // Method kotlin/jvm/internal/Intrinsics.checkParameterIsNotNull:(Ljava/lang/Object;Ljava/lang/String;)V
       6: new           #34                 // class com/typosafe/java/Pojo
       9: dup
      10: invokespecial #38                 // Method com/typosafe/java/Pojo."<init>":()V
      13: astore_2
      14: getstatic     #44                 // Field com/typosafe/Instances.logins:Ljava/util/List;
      17: invokeinterface #50,  1           // InterfaceMethod java/util/List.iterator:()Ljava/util/Iterator;
      22: astore        4
      24: aload         4
      26: invokeinterface #56,  1           // InterfaceMethod java/util/Iterator.hasNext:()Z
      31: ifeq          57
      34: aload         4
      36: invokeinterface #60,  1           // InterfaceMethod java/util/Iterator.next:()Ljava/lang/Object;
      41: checkcast     #62                 // class java/lang/String
      44: astore_3
      45: aload_1
      46: aload_2
      47: aload_3
      48: invokestatic  #66                 // Method com/typosafe/java/Pojo.updateFromLoginStatic:(Lcom/typosafe/java/Pojo;Ljava/lang/String;)Ljava/lang/String;
      51: invokevirtual #72                 // Method org/openjdk/jmh/infra/Blackhole.consume:(Ljava/lang/Object;)V
      54: goto          24
      57: return

  public final void kotlinExtensionFunction(org.openjdk.jmh.infra.Blackhole);
    Code:
       0: aload_1
       1: ldc           #26                 // String bh
       3: invokestatic  #32                 // Method kotlin/jvm/internal/Intrinsics.checkParameterIsNotNull:(Ljava/lang/Object;Ljava/lang/String;)V
       6: new           #34                 // class com/typosafe/java/Pojo
       9: dup
      10: invokespecial #38                 // Method com/typosafe/java/Pojo."<init>":()V
      13: astore_2
      14: getstatic     #44                 // Field com/typosafe/Instances.logins:Ljava/util/List;
      17: invokeinterface #50,  1           // InterfaceMethod java/util/List.iterator:()Ljava/util/Iterator;
      22: astore        4
      24: aload         4
      26: invokeinterface #56,  1           // InterfaceMethod java/util/Iterator.hasNext:()Z
      31: ifeq          63
      34: aload         4
      36: invokeinterface #60,  1           // InterfaceMethod java/util/Iterator.next:()Ljava/lang/Object;
      41: checkcast     #62                 // class java/lang/String
      44: astore_3
      45: aload_1
      46: aload_2
      47: aload_3
      48: dup
      49: ldc           #81                 // String login
      51: invokestatic  #84                 // Method kotlin/jvm/internal/Intrinsics.checkExpressionValueIsNotNull:(Ljava/lang/Object;Ljava/lang/String;)V
      54: invokestatic  #89                 // Method com/typosafe/java/JavaExtKt.updateFromLoginExt:(Lcom/typosafe/java/Pojo;Ljava/lang/String;)Ljava/lang/String;
      57: invokevirtual #72                 // Method org/openjdk/jmh/infra/Blackhole.consume:(Ljava/lang/Object;)V
      60: goto          24
      63: return

  public final void kotlinCompanionObject(org.openjdk.jmh.infra.Blackhole);
    Code:
       0: aload_1
       1: ldc           #26                 // String bh
       3: invokestatic  #32                 // Method kotlin/jvm/internal/Intrinsics.checkParameterIsNotNull:(Ljava/lang/Object;Ljava/lang/String;)V
       6: new           #92                 // class com/typosafe/kotlin/Pojo
       9: dup
      10: invokespecial #93                 // Method com/typosafe/kotlin/Pojo."<init>":()V
      13: astore_2
      14: getstatic     #44                 // Field com/typosafe/Instances.logins:Ljava/util/List;
      17: invokeinterface #50,  1           // InterfaceMethod java/util/List.iterator:()Ljava/util/Iterator;
      22: astore        4
      24: aload         4
      26: invokeinterface #56,  1           // InterfaceMethod java/util/Iterator.hasNext:()Z
      31: ifeq          66
      34: aload         4
      36: invokeinterface #60,  1           // InterfaceMethod java/util/Iterator.next:()Ljava/lang/Object;
      41: checkcast     #62                 // class java/lang/String
      44: astore_3
      45: aload_1
      46: getstatic     #97                 // Field com/typosafe/kotlin/Pojo.Companion:Lcom/typosafe/kotlin/Pojo$Companion;
      49: aload_2
      50: aload_3
      51: dup
      52: ldc           #81                 // String login
      54: invokestatic  #84                 // Method kotlin/jvm/internal/Intrinsics.checkExpressionValueIsNotNull:(Ljava/lang/Object;Ljava/lang/String;)V
      57: invokevirtual #103                // Method com/typosafe/kotlin/Pojo$Companion.updateFromLoginCompanion:(Lcom/typosafe/kotlin/Pojo;Ljava/lang/String;)Ljava/lang/String;
      60: invokevirtual #72                 // Method org/openjdk/jmh/infra/Blackhole.consume:(Ljava/lang/Object;)V
      63: goto          24
      66: return

  public com.typosafe.jmh.ExtensionMethodsBench();
    Code:
       0: aload_0
       1: invokespecial #105                // Method java/lang/Object."<init>":()V
       4: return
}
